unigen/__init__.py
unigen/types/__init__.py
unigen/types/audio_metadata.py
unigen/types/picture.py
unigen/wrapper/__init__.py
unigen/wrapper/audio_factory.py
unigen/wrapper/audio_manager.py
unigen/wrapper/id3.py
unigen/wrapper/mp4.py
unigen/wrapper/utils.py
unigen/wrapper/vorbis.py
unigen-1.4.4.2.dist-info/LICENSE
unigen-1.4.4.2.dist-info/METADATA
unigen-1.4.4.2.dist-info/WHEEL
unigen-1.4.4.2.dist-info/top_level.txt
unigen-1.4.4.2.dist-info/RECORD
