Metadata-Version: 2.1
Name: unigen
Version: 1.4.4.2
License-File: LICENSE
Requires-Dist: mutagen
